{
  "project_info": {
    "project_number": "529775655888",
    "project_id": "thptexamprepapp",
    "storage_bucket": "thptexamprepapp.firebasestorage.app"
  },
  "client": [
    {
      "client_info": {
        "mobilesdk_app_id": "1:529775655888:android:5085cee4bf39d9a51497d5",
        "android_client_info": {
          "package_name": "com.example.thpt_exam_prep_app"
        }
      },
      "oauth_client": [],
      "api_key": [
        {
          "current_key": "AIzaSyAunczv2aEIwkv4UYO4Gbh2IOXX0Nr5MYA"
        }
      ],
      "services": {
        "appinvite_service": {
          "other_platform_oauth_client": []
        }
      }
    }
  ],
  "configuration_version": "1"
}